dewar/__init__.py
dewar/_internal.py
dewar/dewar.py
dewar/exceptions.py
dewar/helpers.py
dewar/jinja.py
dewar/parser.py
dewar/validator.py
dewar-1.2.1.dist-info/LICENSE.txt
dewar-1.2.1.dist-info/METADATA
dewar-1.2.1.dist-info/WHEEL
dewar-1.2.1.dist-info/top_level.txt
dewar-1.2.1.dist-info/RECORD
