Metadata-Version: 2.1
Name: dewar
Version: 1.2.1
Summary: Static Site Generator, like flask
Home-page: https://github.com/tfpk/dewar
Author: tfpk
Author-email: tomkunc0@gmail.com
License: Apache 2.0
Platform: UNKNOWN
Classifier: License :: OSI Approved :: Apache Software License
Classifier: Programming Language :: Python
Classifier: Programming Language :: Python :: 3
Classifier: Programming Language :: Python :: 3.6
Classifier: Programming Language :: Python :: Implementation :: CPython
Classifier: Programming Language :: Python :: Implementation :: PyPy
Requires-Python: >=3.6.0
Requires-Dist: markdown
Requires-Dist: proxy-tools
Requires-Dist: jinja2
Provides-Extra: dev
Requires-Dist: sphinx ; extra == 'dev'
Provides-Extra: docs
Requires-Dist: sphinx ; extra == 'docs'
